observable_models/__init__.py
observable_models/apps.py
observable_models/models.py
django_observable_models-0.4.0.dist-info/WHEEL
django_observable_models-0.4.0.dist-info/METADATA
django_observable_models-0.4.0.dist-info/RECORD
