Metadata-Version: 2.1
Name: django-observable-models
Version: 0.4.0
Summary: 
Author: Jayden Windle
Author-email: jaydenwindle@gmail.com
Requires-Python: >=3.6,<4.0
Classifier: Programming Language :: Python :: 3
Classifier: Programming Language :: Python :: 3.6
Classifier: Programming Language :: Python :: 3.7
Requires-Dist: django (>=3.0,<4.0)
Requires-Dist: rx (==1.6.1)
